openstef/__init__.py
openstef/__main__.py
openstef/app_settings.py
openstef/enums.py
openstef/exceptions.py
openstef/settings.py
openstef/data/NL_terrestrial_radiation.csv
openstef/data/NL_terrestrial_radiation.csv.license
openstef/data/dutch_holidays.csv
openstef/data/dutch_holidays.csv.license
openstef/data/pv_single_coefs.csv
openstef/data/pv_single_coefs.csv.license
openstef/data/dazls_model_3.4.24/dazls_stored_3.4.24_baseline_model.z
openstef/data/dazls_model_3.4.24/dazls_stored_3.4.24_baseline_model.z.license
openstef/data/dazls_model_3.4.24/dazls_stored_3.4.24_model_card.md
openstef/data/dazls_model_3.4.24/dazls_stored_3.4.24_model_card.md.license
openstef/data_classes/__init__.py
openstef/data_classes/data_prep.py
openstef/data_classes/model_specifications.py
openstef/data_classes/prediction_job.py
openstef/data_classes/split_function.py
openstef/feature_engineering/__init__.py
openstef/feature_engineering/apply_features.py
openstef/feature_engineering/bidding_zone_to_country_mapping.py
openstef/feature_engineering/cyclic_features.py
openstef/feature_engineering/data_preparation.py
openstef/feature_engineering/feature_adder.py
openstef/feature_engineering/feature_applicator.py
openstef/feature_engineering/general.py
openstef/feature_engineering/holiday_features.py
openstef/feature_engineering/lag_features.py
openstef/feature_engineering/missing_values_transformer.py
openstef/feature_engineering/rolling_features.py
openstef/feature_engineering/weather_features.py
openstef/logging/__init__.py
openstef/logging/base_logger.py
openstef/logging/logger_factory.py
openstef/logging/logger_types.py
openstef/logging/standard_logger.py
openstef/logging/structlog_logger.py
openstef/metrics/__init__.py
openstef/metrics/figure.py
openstef/metrics/metrics.py
openstef/metrics/reporter.py
openstef/model/__init__.py
openstef/model/basecase.py
openstef/model/confidence_interval_applicator.py
openstef/model/fallback.py
openstef/model/model_creator.py
openstef/model/objective.py
openstef-3.4.92.dist-info/licenses/LICENSE
openstef-3.4.92.dist-info/METADATA
openstef-3.4.92.dist-info/WHEEL
openstef-3.4.92.dist-info/top_level.txt
openstef-3.4.92.dist-info/RECORD
