Metadata-Version: 2.4
Name: openstef
Version: 3.4.92
Summary: Open short term energy forecaster
Home-page: https://github.com/OpenSTEF/openstef
Author: Alliander N.V
Author-email: openstef@lfenergy.org
License: MPL-2.0
Keywords: energy,forecasting,machinelearning
Classifier: Development Status :: 5 - Production/Stable
Classifier: Intended Audience :: Developers
Classifier: License :: OSI Approved :: Mozilla Public License 2.0 (MPL 2.0)
Classifier: Programming Language :: Python :: 3.11
Requires-Python: >=3.11.0
License-File: LICENSE
Requires-Dist: holidays==0.21
Requires-Dist: joblib==1.3.2
Requires-Dist: lightgbm>=4.0
Requires-Dist: matplotlib~=3.7
Requires-Dist: mlflow-skinny<4.0,>=2.0
Requires-Dist: networkx~=3.1
Requires-Dist: numpy<3,>=2
Requires-Dist: optuna~=3.1
Requires-Dist: optuna-integration~=3.6
Requires-Dist: pandas~=2.2.0
Requires-Dist: plotly~=5.18
Requires-Dist: pvlib==0.10.5
Requires-Dist: pydantic~=2.4
Requires-Dist: pydantic-settings~=2.3
Requires-Dist: pymsteams~=0.2.2
Requires-Dist: scikit-learn<1.6,>=1.3
Requires-Dist: scipy~=1.10
Requires-Dist: statsmodels<1.0.0,>=0.13.5
Requires-Dist: structlog>=23.1
Requires-Dist: xgboost~=2.0; extra == "gpu"
Provides-Extra: cpu
Requires-Dist: xgboost-cpu~=2.0; extra == "cpu"
Provides-Extra: gpu
Requires-Dist: xgboost; extra == "gpu"
Provides-Extra: mlflow-full
Requires-Dist: mlflow<4.0,>=2.0; extra == "mlflow-full"
Dynamic: author
Dynamic: author-email
Dynamic: classifier
Dynamic: description
Dynamic: description-content-type
Dynamic: home-page
Dynamic: keywords
Dynamic: license
Dynamic: license-file
Dynamic: provides-extra
Dynamic: requires-dist
Dynamic: requires-python
Dynamic: summary
